TikTokWebSign/TikTokWebSign.py
TikTokWebSign/__init__.py
TikTokWebSign/test.py
tiktokwebsign-0.1.0.dist-info/METADATA
tiktokwebsign-0.1.0.dist-info/WHEEL
tiktokwebsign-0.1.0.dist-info/top_level.txt
tiktokwebsign-0.1.0.dist-info/RECORD
