Metadata-Version: 2.4
Name: TikTokWebSign
Version: 0.1.0
Summary: TikTok Web signatures Algorithm
Author-email: ked <noone@gmail.com>
License: MIT
Project-URL: Homepage, https://github.com/kedd
Project-URL: Repository, https://github.com/keddn/TikTok-USER-WebAloghrim
Keywords: tiktok,signature,web,x-bogus,x-gnarly,Tiksign,username
Requires-Python: >=3.8
